[
  {
    "title": "",
    "inline": true,
    "backgroundColor": "#f2f2f2",
    "color": "#323232",
    "rowItems": [
      {
        "imgUrl": "http://d2trtkcohkrm90.cloudfront.net/images/emoji/apple/ios-10/256/beer-mug.png",
        "text": "Black",
        "highlight": false
      },
      {
        "text": "San Jose, CA <span style='padding-left: 10px; color:green !important;'>↑</span>",
        "highlight": false
      },
      {
        "text": "Lake Charles, LA <span style='padding-left: 10px; color:red !important;'>↓</span>",
        "highlight": false
      },
      {
        "text": "Provo, UT <span style='padding-left: 10px; color:red !important;'>↓</span>",
        "highlight": false
      },
      {
        "text": "Santa Rosa, CA <span style='padding-left: 10px; color:green !important;'>↑</span>",
        "highlight": false
      }
    ]
  },
  {
    "inline": true,
    "backgroundColor": "#d3d5d5",
    "color": "#323232",
    "rowItems": [
      {
        "text": "9.40%",
        "highlight": true
      },
      {
        "text": "8.90%",
        "highlight": true
      },
      {
        "text": "8.30%",
        "highlight": true
      },
      {
        "text": "7.60%",
        "highlight": true
      },
      {
        "text": "7.20%",
        "highlight": true
      }
    ]
  },
  {
    "inline": true,
    "backgroundColor": "#d3d5d5",
    "color": "#323232",
    "rowItems": [
      {
        "text": "$25.58B",
        "highlight": true
      },
      {
        "text": "$223.09B",
        "highlight": true
      },
      {
        "text": "$12.37B",
        "highlight": true
      },
      {
        "text": "$18.63B",
        "highlight": true
      },
      {
        "text": "$23.46B",
        "highlight": true
      }
    ]
  },
  {
    "inline": true,
    "backgroundColor": "#d3d5d5",
    "color": "#323232",
    "rowItems": [
      {
        "text": "8.2%",
        "highlight": true
      },
      {
        "text": "16.3%",
        "highlight": true
      },
      {
        "text": "10.6%",
        "highlight": true
      },
      {
        "text": "11.7%",
        "highlight": true
      },
      {
        "text": "14.4%",
        "highlight": true
      }
    ]
  }
]
